README.rst
setup.py
jsonpath_rw/VERSION
jsonpath_rw/__init__.py
jsonpath_rw/jsonpath.py
jsonpath_rw/lexer.py
jsonpath_rw/parser.py
jsonpath_rw/version.py
jsonpath_rw.egg-info/PKG-INFO
jsonpath_rw.egg-info/SOURCES.txt
jsonpath_rw.egg-info/dependency_links.txt
jsonpath_rw.egg-info/requires.txt
jsonpath_rw.egg-info/top_level.txt