Metadata-Version: 1.1
Name: jsonpath-rw
Version: 1.2.2
Summary: A robust and significantly extended implementation of JSONPath for Python, with a clear AST for metaprogramming.
Home-page: https://github.com/kennknowles/python-jsonpath-rw
Author: Kenneth Knowles
Author-email: kenn.knowles@gmail.com
License: Apache 2.0
Platform: UNKNOWN
Classifier: Development Status :: 5 - Production/Stable
Classifier: Intended Audience :: Developers
Classifier: License :: OSI Approved :: Apache Software License
Classifier: Programming Language :: Python :: 2
Classifier: Programming Language :: Python :: 2.6
Classifier: Programming Language :: Python :: 2.7
Classifier: Programming Language :: Python :: 3
Classifier: Programming Language :: Python :: 3.2
Classifier: Programming Language :: Python :: 3.3
